{"cameraMode":{"drawMode":0,"name":"Shaded","section":"Shading Mode"},"sceneLighting":true,"audioPlay":false,"sceneViewState":{"m_AlwaysRefresh":false,"showFog":true,"showSkybox":true,"showFlares":true,"showImageEffects":true,"showParticleSystems":true,"showVisualEffectGraphs":true,"m_FxEnabled":true},"in2DMode":false,"pivot":{"x":-1.887317180633545,"y":3.129519462585449,"z":-5.4224395751953129},"rotation":{"x":-0.08564504235982895,"y":-0.7526769638061523,"z":0.09994214028120041,"w":-0.6451206803321838},"size":2.805432081222534,"orthographic":false}